whatsapp_utilsFAPI/__init__.py
whatsapp_utilsFAPI/utils/LLM.py
whatsapp_utilsFAPI/utils/STT.py
whatsapp_utilsFAPI/utils/TTS.py
whatsapp_utilsFAPI/utils/__init__.py
whatsapp_utilsFAPI/utils/utils.py
whatsapp_utilsfapi-0.36.0.dist-info/licenses/LICENSE
whatsapp_utilsfapi-0.36.0.dist-info/METADATA
whatsapp_utilsfapi-0.36.0.dist-info/WHEEL
whatsapp_utilsfapi-0.36.0.dist-info/top_level.txt
whatsapp_utilsfapi-0.36.0.dist-info/RECORD
