Metadata-Version: 2.4
Name: whatsapp_utilsFAPI
Version: 0.36.0
Summary: whatsapp_utilsFAPI
Author: whatsapp_utilsFAPI
License: MIT
Classifier: Programming Language :: Python :: 3
Classifier: License :: OSI Approved :: MIT License
Classifier: Operating System :: OS Independent
Requires-Python: >=3.11
License-File: LICENSE
Dynamic: license-file
